asf/__init__.py
asf/cli/__init__.py
asf/cli/cli_train.py
asf/epm/__init__.py
asf/epm/epm.py
asf/epm/epm_tuner.py
asf/metrics/__init__.py
asf/metrics/baselines.py
asf/pre_selector/__init__.py
asf/pre_selector/abstract_pre_selector.py
asf/pre_selector/beam_search_pre_selection.py
asf/pre_selector/brute_force_pre_selection.py
asf/pre_selector/knee_of_the_curve_pre_selector.py
asf/pre_selector/marginal_contribution_based.py
asf/pre_selector/optimize_pre_selection.py
asf/pre_selector/sbs_pre_selection.py
asf/predictors/__init__.py
asf/predictors/abstract_predictor.py
asf/predictors/epm_extra_trees.py
asf/predictors/epm_random_forest.py
asf/predictors/linear_model.py
asf/predictors/mlp.py
asf/predictors/random_forest.py
asf/predictors/ranking_mlp.py
asf/predictors/regression_mlp.py
asf/predictors/sklearn_wrapper.py
asf/predictors/svm.py
asf/predictors/xgboost.py
asf/predictors/utils/datasets.py
asf/predictors/utils/losses.py
asf/predictors/utils/mlp.py
asf/preprocessing/__init__.py
asf/preprocessing/performace_scaling.py
asf/preprocessing/sklearn_preprocessor.py
asf/presolving/__init__.py
asf/presolving/asap_v2.py
asf/presolving/aspeed.py
asf/presolving/presolver.py
asf/scenario/__init__.py
asf/scenario/aslib_reader.py
asf/scenario/epmbench_reader.py
asf/selectors/__init__.py
asf/selectors/abstract_model_based_selector.py
asf/selectors/abstract_selector.py
asf/selectors/feature_generator.py
asf/selectors/joint_ranking.py
asf/selectors/mutli_class.py
asf/selectors/pairwise_classifier.py
asf/selectors/pairwise_regressor.py
asf/selectors/performance_model.py
asf/selectors/selector_pipeline.py
asf/selectors/selector_tuner.py
asf/selectors/simple_ranking.py
asf/selectors/survival_analysis.py
asf/utils/groupkfoldshuffle.py
asf_lib-0.1.1.dist-info/licenses/LICENSE
asf_lib-0.1.1.dist-info/METADATA
asf_lib-0.1.1.dist-info/WHEEL
asf_lib-0.1.1.dist-info/top_level.txt
asf_lib-0.1.1.dist-info/RECORD
